Metadata-Version: 1.0
Name: mailDropper
Version: 1.1.0
Summary: UNKNOWN
Home-page: https://github.com/katkamrachana/mailDropper
Author: katkamrachana
Author-email: katkam.rachana@gmail.com
License: AGPL 3.0
Keywords: email,bulk,custom
Platform: UNKNOWN
